snaparg/__init__.py
snaparg/snaparg.py
snaparg-0.2.0.dist-info/licenses/LICENSE
snaparg-0.2.0.dist-info/METADATA
snaparg-0.2.0.dist-info/WHEEL
snaparg-0.2.0.dist-info/top_level.txt
snaparg-0.2.0.dist-info/RECORD
