Metadata-Version: 2.4
Name: snaparg
Version: 0.2.0
Summary: A typo-tolerant CLI parser wrapper for argparse
Author: PJ Hayes
Author-email: PJ Hayes <archood2next@gmail.com>
License: MPL 2.0
Requires-Python: >=3.6
License-File: LICENSE
Dynamic: author
Dynamic: license-file
Dynamic: requires-python
